OpencvJishiRumenChuyi/README.md
OpencvJishiRumenChuyi/__init__.py
OpencvJishiRumenChuyi/__main__.py
OpencvJishiRumenChuyi/file.epub
OpencvJishiRumenChuyi/index.html
OpencvJishiRumenChuyi/css/__init__.py
OpencvJishiRumenChuyi/css/annotations.css
OpencvJishiRumenChuyi/css/main.css
OpencvJishiRumenChuyi/css/normalize.css
OpencvJishiRumenChuyi/css/popup.css
OpencvJishiRumenChuyi/font/__init__.py
OpencvJishiRumenChuyi/font/fontello.eot
OpencvJishiRumenChuyi/font/fontello.svg
OpencvJishiRumenChuyi/font/fontello.ttf
OpencvJishiRumenChuyi/font/fontello.woff
OpencvJishiRumenChuyi/img/__init__.py
OpencvJishiRumenChuyi/img/annotator-glyph-sprite.png
OpencvJishiRumenChuyi/img/annotator-icon-sprite.png
OpencvJishiRumenChuyi/img/apple-touch-icon.png
OpencvJishiRumenChuyi/img/cancelfullscreen.png
OpencvJishiRumenChuyi/img/close.png
OpencvJishiRumenChuyi/img/fullscreen.png
OpencvJishiRumenChuyi/img/loader.gif
OpencvJishiRumenChuyi/img/menu-icon.png
OpencvJishiRumenChuyi/img/save.png
OpencvJishiRumenChuyi/img/saved.png
OpencvJishiRumenChuyi/img/settings-s.png
OpencvJishiRumenChuyi/img/settings.png
OpencvJishiRumenChuyi/img/star.png
OpencvJishiRumenChuyi/js/__init__.py
OpencvJishiRumenChuyi/js/epub.js
OpencvJishiRumenChuyi/js/epub.min.js
OpencvJishiRumenChuyi/js/epub.min.map
OpencvJishiRumenChuyi/js/hooks.min.js
OpencvJishiRumenChuyi/js/hooks.min.map
OpencvJishiRumenChuyi/js/reader.js
OpencvJishiRumenChuyi/js/reader.js.map
OpencvJishiRumenChuyi/js/reader.min.js
OpencvJishiRumenChuyi/js/reader.min.map
OpencvJishiRumenChuyi/js/hooks/__init__.py
OpencvJishiRumenChuyi/js/hooks/extensions/__init__.py
OpencvJishiRumenChuyi/js/hooks/extensions/highlight.js
OpencvJishiRumenChuyi/js/libs/__init__.py
OpencvJishiRumenChuyi/js/libs/jquery.min.js
OpencvJishiRumenChuyi/js/libs/localforage.min.js
OpencvJishiRumenChuyi/js/libs/screenfull.js
OpencvJishiRumenChuyi/js/libs/screenfull.min.js
OpencvJishiRumenChuyi/js/libs/zip.min.js
OpencvJishiRumenChuyi/js/plugins/__init__.py
opencv_jishi_rumen_chuyi-2024.3.6.0.dist-info/METADATA
opencv_jishi_rumen_chuyi-2024.3.6.0.dist-info/WHEEL
opencv_jishi_rumen_chuyi-2024.3.6.0.dist-info/entry_points.txt
opencv_jishi_rumen_chuyi-2024.3.6.0.dist-info/top_level.txt
opencv_jishi_rumen_chuyi-2024.3.6.0.dist-info/RECORD
